converse/__init__.py
converse/admin.py
converse/apps.py
converse/executors.py
converse/messengers.py
converse/models.py
converse/parsers.py
converse/tasks.py
converse/tests.py
converse/urls.py
converse/views.py
converse/migrations/0001_initial.py
converse/migrations/0002_group_name.py
converse/migrations/0003_slackuser_slack_channel.py
converse/migrations/__init__.py
django_bot-0.2.2.dist-info/DESCRIPTION.rst
django_bot-0.2.2.dist-info/METADATA
django_bot-0.2.2.dist-info/RECORD
django_bot-0.2.2.dist-info/WHEEL
django_bot-0.2.2.dist-info/metadata.json
django_bot-0.2.2.dist-info/top_level.txt
