Metadata-Version: 2.0
Name: django-bot
Version: 0.2.2
Summary: A lightweight django framework for bots
Home-page: https://github.com/shaileshahuja/django-bot
Author: shaileshahuja
Author-email: shailesh.ahuja03@gmail.com
License: GNU General Public License v3.0
Platform: UNKNOWN
Classifier: Environment :: Other Environment
Classifier: Framework :: Django
Classifier: Framework :: Django :: 1.8
Classifier: Framework :: Django :: 1.9
Classifier: Framework :: Django :: 1.10
Classifier: Framework :: Django :: 1.11
Classifier: Intended Audience :: Developers
Classifier: License :: OSI Approved :: GNU General Public License v3 (GPLv3)
Classifier: Operating System :: OS Independent
Classifier: Programming Language :: Python
Classifier: Programming Language :: Python :: 2
Classifier: Programming Language :: Python :: 2.7
Classifier: Programming Language :: Python :: 3
Classifier: Programming Language :: Python :: 3.4
Classifier: Programming Language :: Python :: 3.5
Classifier: Programming Language :: Python :: 3.6
Classifier: Topic :: Communications
Classifier: Topic :: Communications :: Chat
Classifier: Topic :: Software Development
Classifier: Topic :: Software Development :: Libraries
Requires-Dist: celery (>=4.0)
Requires-Dist: slackclient (==1.0.5)
Requires-Dist: Django (>=1.8)
Requires-Dist: apiai (==1.2.3)
